lqs/__init__.py
lqs/__main__.py
lqs/client/__init__.py
lqs/client/__main__.py
lqs/client/client.py
lqs/client/common.py
lqs/client/config.py
lqs/client/server.py
lqs/client/utils.py
lqs/client/admin/__init__.py
lqs/client/admin/admin.py
lqs/client/admin/create.py
lqs/client/core/__init__.py
lqs/client/core/core.py
lqs/client/core/create.py
lqs/client/core/delete.py
lqs/client/core/fetch.py
lqs/client/core/list.py
lqs/client/core/studio.py
lqs/client/core/update.py
lqs/client/dsm/__init__.py
lqs/client/dsm/create.py
lqs/client/dsm/delete.py
lqs/client/dsm/dsm.py
lqs/client/dsm/fetch.py
lqs/client/dsm/list.py
lqs/client/dsm/update.py
lqs/common/__init__.py
lqs/common/config.py
lqs/common/core_utils.py
lqs/common/exceptions.py
lqs/common/facade.py
lqs/common/utils/__init__.py
lqs/common/utils/crud_utils.py
lqs/common/utils/digestion_utils.py
lqs/common/utils/ingestion_utils.py
lqs/common/utils/object_utils.py
lqs/common/utils/record_utils.py
lqs/common/utils/utils.py
lqs/interface/__init__.py
lqs/interface/admin/__init__.py
lqs/interface/admin/create.py
lqs/interface/admin/models/__init__.py
lqs/interface/admin/models/command.py
lqs/interface/base/__init__.py
lqs/interface/base/create.py
lqs/interface/base/delete.py
lqs/interface/base/fetch.py
lqs/interface/base/list.py
lqs/interface/base/update.py
lqs/interface/base/models/__common__.py
lqs/interface/base/models/__init__.py
lqs/interface/base/models/api_key.py
lqs/interface/base/models/role.py
lqs/interface/base/models/user.py
lqs/interface/core/__init__.py
lqs/interface/core/create.py
lqs/interface/core/delete.py
lqs/interface/core/fetch.py
lqs/interface/core/list.py
lqs/interface/core/studio.py
lqs/interface/core/update.py
lqs/interface/core/models/__common__.py
lqs/interface/core/models/__init__.py
lqs/interface/core/models/api_key.py
lqs/interface/core/models/callback.py
lqs/interface/core/models/digestion.py
lqs/interface/core/models/digestion_part.py
lqs/interface/core/models/digestion_topic.py
logqs-1.1.11.dist-info/METADATA
logqs-1.1.11.dist-info/WHEEL
logqs-1.1.11.dist-info/entry_points.txt
logqs-1.1.11.dist-info/top_level.txt
logqs-1.1.11.dist-info/RECORD
