Metadata-Version: 2.4
Name: LogQS
Version: 1.1.11
Summary: A client for interacting with the LogQS Service.
Home-page: https://github.com/carnegierobotics/LogQS
Author: Nathan Margaglio
Author-email: nmargaglio@carnegierobotics.com
Project-URL: Bug Tracker, https://github.com/carnegierobotics/LogQS/issues
Classifier: Programming Language :: Python :: 3
Classifier: License :: OSI Approved :: MIT License
Classifier: Operating System :: OS Independent
Requires-Python: >=3.9
Requires-Dist: av>=10.0.0
Requires-Dist: antlr4-python3-runtime<5.0.0,>=4.13.0
Requires-Dist: cattrs<24.0.0,>=23.2.3
Requires-Dist: crc32c<3.0.0,>=2.0.0
Requires-Dist: ciso8601<3.0.0,>=2.0.0
Requires-Dist: DracoPy<2.0.0,>=1.0.0
Requires-Dist: fastapi<1.0.0,>=0.101.0
Requires-Dist: fire<0.6.0,>=0.4.0
Requires-Dist: lz4<5.0.0,>=4.0.0
Requires-Dist: mangum<1.0.0,>=0.17.0
Requires-Dist: mcap<2.0.0,>=1.1.1
Requires-Dist: numpy<3.0.0,>=2.0.0
Requires-Dist: orjson<4.0.0,>=3.0.0
Requires-Dist: Pillow<11.0.0,>=10.0.0
Requires-Dist: psutil<8.0.0,>=6.0.0
Requires-Dist: pydantic<3.0.0,>=2.0.0
Requires-Dist: pydantic-settings<3.0.0,>=2.0.0
Requires-Dist: python-json-logger<3.0.0,>=2.0.0
Requires-Dist: requests<3.0.0,>=2.0.0
Requires-Dist: rosbags<0.11.0,>=0.10.0
Requires-Dist: s3path<1.0.0,>=0.5.0
Requires-Dist: tqdm<5.0.0,>=4.0.0
Requires-Dist: uvicorn<1.0.0,>=0.23.0
Requires-Dist: zstandard<1.0.0,>=0.1.0
Requires-Dist: zstd<2.0.0,>=1.0.0
Dynamic: author
Dynamic: author-email
Dynamic: classifier
Dynamic: description
Dynamic: description-content-type
Dynamic: home-page
Dynamic: project-url
Dynamic: requires-dist
Dynamic: requires-python
Dynamic: summary
